{
  "resources": [
    {
      "path": "data.csv",
      "name": "data",
      "profile": "tabular-data-resource",
      "scheme": "file",
      "format": "csv",
      "hashing": "md5",
      "encoding": "utf-8",
      "schema": {
        "fields": [
          {
            "name": "COMPOSITE_BREAKDOWN",
            "type": "string",
            "constraints": {
              "enum": [
                "",
                "Legislation and financing",
                "IHR Coordination and National Focal Point Functions",
                "Zoonotic events and the Human-Animal Health Interface",
                "Food safety",
                "Laboratory",
                "Surveillance",
                "Human resources",
                "National Health Emergency Framework",
                "Health Service Provision",
                "Risk communication",
                "Points of entry",
                "Chemical events",
                "Radiation emergencies"
              ]
            },
            "title": "Composite breakdown"
          },
          {
            "name": "SERIES",
            "type": "string",
            "title": "SDG Series"
          },
          {
            "name": "Value",
            "type": "integer",
            "title": "Value"
          },
          {
            "name": "Year",
            "type": "string",
            "title": "Year"
          }
        ]
      }
    }
  ],
  "profile": "data-package",
  "name": "3-d-1",
  "title": "International Health Regulations (IHR) capacity and health emergency preparedness"
}